reclassification/reclassification.py
reclassification/test_reclassification.py
reclassification-0.2.dist-info/LICENSE.txt
reclassification-0.2.dist-info/METADATA
reclassification-0.2.dist-info/WHEEL
reclassification-0.2.dist-info/top_level.txt
reclassification-0.2.dist-info/RECORD
